flatgraphene/__init__.py
flatgraphene/help_doc.md
flatgraphene/hhelp.py
flatgraphene/shift.py
flatgraphene/twist.py
flatgraphene/twist_legacy.py
flatgraphene-0.3.6.data/scripts/flatgraphene
tests/__init__.py
tests/context.py
tests/test_shift.py
tests/test_twist.py
flatgraphene-0.3.6.dist-info/LICENSE
flatgraphene-0.3.6.dist-info/METADATA
flatgraphene-0.3.6.dist-info/WHEEL
flatgraphene-0.3.6.dist-info/top_level.txt
flatgraphene-0.3.6.dist-info/RECORD
