Metadata-Version: 2.1
Name: flatgraphene
Version: 0.3.6
Summary: Generate mono and multilayer graphene geometries
Home-page: https://github.com/Johnson-Research-Group/flat-graphene
Author: Gabriel H. Brown
Author-email: gabriel.h.brown@gmail.com
License: UNKNOWN
Keywords: twisted,bilayer,graphene,graphite,scientific,engineering,molecular dynamics,atomistic
Platform: UNKNOWN
Classifier: Programming Language :: Python :: 3
Classifier: License :: OSI Approved :: MIT License
Classifier: Operating System :: OS Independent
Classifier: Topic :: Scientific/Engineering
License-File: LICENSE
Requires-Dist: numpy
Requires-Dist: ase
